async_orchestrator/__init__.py
async_orchestrator/async_orchestrator.py
async_orchestrator/auth.py
async_orchestrator/client.py
async_orchestrator/resource.py
orchestrator/__init__.py
orchestrator/auth.py
orchestrator/client.py
orchestrator/orchestrator.py
orchestrator/orchestrator_resource.py
python_orchestrator-1.0.0.dist-info/LICENSE.txt
python_orchestrator-1.0.0.dist-info/METADATA
python_orchestrator-1.0.0.dist-info/WHEEL
python_orchestrator-1.0.0.dist-info/top_level.txt
python_orchestrator-1.0.0.dist-info/RECORD
